filesocket/__init__.py
filesocket/__main__.py
filesocket/config.py
filesocket/exceptions.py
filesocket/managed_device_client.py
filesocket/managing_device_client.py
filesocket/storekeeper.py
filesocket-0.1.8.dist-info/LICENSE
filesocket-0.1.8.dist-info/METADATA
filesocket-0.1.8.dist-info/WHEEL
filesocket-0.1.8.dist-info/top_level.txt
filesocket-0.1.8.dist-info/RECORD
