Metadata-Version: 2.1
Name: filesocket
Version: 0.1.8
Summary: Transferring data between PCs library
Home-page: https://github.com/Qolorerr/FileSocketClient
Author: Mikhail Ivanov
Author-email: qolorer@gmail.com
License: UNKNOWN
Platform: UNKNOWN
Classifier: Programming Language :: Python :: 3
Classifier: License :: OSI Approved :: MIT License
Classifier: Operating System :: OS Independent
License-File: LICENSE
Requires-Dist: requests (>=2.28.1)
Requires-Dist: pyngrok (>=5.2.1)
Requires-Dist: uvicorn (>=0.20.0)
Requires-Dist: fastapi (>=0.89.1)
Requires-Dist: starlette (>=0.22.0)
Requires-Dist: python-multipart (>=0.0.5)
